{
    "name": "Harley",
    "class": "Assassin",
    "attack_type": "Magical",
    "additional_effects": "",
    "recommended_items": [],
    "base_stats": {},
    "skills": {
        "passive": {
            "name": "Magic Master",
            "description": "Базові атаки Харлі знижують магічний захист цілі на 2, що може накопичуватися до 10 разів."
        },
        "skill1": {
            "name": "Poker Trick",
            "description": "Harley випускає 3 карти в обраному напрямку, завдаючи магічного урону першому враженому ворогу. Якщо одна ціль вражена кількома картами, урон зменшується на 20% за кожну наступну карту.",
            "cooldown": "7 секунд.",
            "mana_cost": 90
        },
        "skill2": {
            "name": "Space Escape",
            "description": "Harley телепортується в обране місце, залишаючи магічний капелюх на початковій позиції. Протягом 4 секунд він може повернутися до капелюха, повторно активувавши навичку. Після телепортації його швидкість руху збільшується на 30% на 2 секунди.",
            "cooldown": "13 секунд.",
            "mana_cost": 60
        },
        "ultimate": {
            "name": "Deadly Magic",
            "description": "Harley накладає магічне кільце на обрану ціль, завдаючи магічного урону та створюючи зону, яка триває 4 секунди. Після цього кільце вибухає, завдаючи додаткового урону залежно від урону, отриманого ціллю під час дії навички.",
            "cooldown": "32 секунди.",
            "mana_cost": 120
        }
    }
}
